recbox/__init__.py
recbox/version.py
recbox/core/__init__.py
recbox/core/metrics.py
recbox/core/pytorch/__init__.py
recbox/core/pytorch/layers/__init__.py
recbox/core/pytorch/layers/activations.py
recbox/core/pytorch/layers/embedding.py
recbox/core/pytorch/layers/mlp.py
recbox/core/pytorch/layers/sequence.py
recbox/core/pytorch/losses/__init__.py
recbox/core/pytorch/losses/cosine_contrastive_loss.py
recbox/core/pytorch/losses/mse_loss.py
recbox/core/pytorch/losses/pairwise_logistic_loss.py
recbox/core/pytorch/losses/pairwise_margin_loss.py
recbox/core/pytorch/losses/sigmoid_crossentropy_loss.py
recbox/core/pytorch/losses/softmax_crossentropy_loss.py
recbox/datasets/__init__.py
recbox/datasets/data_utils.py
recbox/matching/__init__.py
recbox/matching/features.py
recbox/matching/preprocess.py
recbox/matching/pytorch/__init__.py
recbox/matching/pytorch/layers.py
recbox/matching/pytorch/dataloaders/__init__.py
recbox/matching/pytorch/dataloaders/h5_generator.py
recbox/matching/pytorch/models/__init__.py
recbox/matching/pytorch/models/match_model.py
recbox/matching/tensorflow/__init__.py
recbox/ranking/__init__.py
recbox/ranking/autotuner.py
recbox/ranking/features.py
recbox/ranking/metrics.py
recbox/ranking/utils.py
recbox/ranking/preprocess/__init__.py
recbox/ranking/preprocess/build_dataset.py
recbox/ranking/preprocess/feature_processor.py
recbox/ranking/preprocess/preprocess_utils.py
recbox/ranking/pytorch/__init__.py
recbox/ranking/pytorch/torch_utils.py
recbox/ranking/pytorch/dataloaders/__init__.py
recbox/ranking/pytorch/dataloaders/h5_block_dataloader.py
recbox/ranking/pytorch/dataloaders/h5_dataloader.py
recbox/ranking/pytorch/layers/__init__.py
recbox/ranking/pytorch/layers/activations.py
recbox/ranking/pytorch/layers/pooling.py
recbox/ranking/pytorch/layers/attentions/__init__.py
recbox/ranking/pytorch/layers/attentions/dot_product_attention.py
recbox/ranking/pytorch/layers/attentions/squeeze_excitation.py
recbox-0.0.4.dist-info/LICENSE
recbox-0.0.4.dist-info/METADATA
recbox-0.0.4.dist-info/WHEEL
recbox-0.0.4.dist-info/top_level.txt
recbox-0.0.4.dist-info/RECORD
